cdrive/Workflow.py
cdrive/__init__.py
cdrive/workflow.py
cdrive-0.0.2.dist-info/LICENSE
cdrive-0.0.2.dist-info/METADATA
cdrive-0.0.2.dist-info/WHEEL
cdrive-0.0.2.dist-info/top_level.txt
cdrive-0.0.2.dist-info/RECORD
