Metadata-Version: 2.1
Name: cdrive
Version: 0.0.2
Summary: Python SDK for CDrive
Home-page: https://github.com/columbustech/cdrive-sdk
Author: Kaushik Chandrasekhar
Author-email: kaushikc92@gmail.com
License: UNKNOWN
Platform: UNKNOWN
Classifier: Programming Language :: Python :: 3
Classifier: License :: OSI Approved :: BSD License
Classifier: Operating System :: OS Independent
Requires-Python: >=3.6
Requires-Dist: requests
